sficopaf/__init__.py
sficopaf/parsing_fw.py
sficopaf/some_parsers.py
sficopaf/utils_not_used.py
sficopaf/var_checker.py
sficopaf-1.0.1.dist-info/DESCRIPTION.rst
sficopaf-1.0.1.dist-info/METADATA
sficopaf-1.0.1.dist-info/RECORD
sficopaf-1.0.1.dist-info/WHEEL
sficopaf-1.0.1.dist-info/metadata.json
sficopaf-1.0.1.dist-info/top_level.txt
