Metadata-Version: 2.0
Name: sficopaf
Version: 1.0.1
Summary: Simple FIle COllection PArsing Framework
Home-page: https://github.com/smarie/python-simple-file-collection-parsing-framework
Author: Sylvain Marié
Author-email: "Sylvain Marié" <sylvain.marie@schneider-electric.com>
License: BSD 3-Clause
Download-URL: https://github.com/smarie/python-simple-file-collection-parsing-framework/tarball/1.0.1
Keywords: file collection parsing framework
Platform: UNKNOWN
Classifier: Development Status :: 3 - Alpha
Classifier: Intended Audience :: Developers
Classifier: Topic :: Software Development :: Libraries :: Python Modules
Classifier: License :: OSI Approved :: BSD License
Classifier: Programming Language :: Python :: 3.5
Provides-Extra: pandas_parser
Requires-Dist: numpy; extra == 'pandas_parser'
Requires-Dist: pandas; extra == 'pandas_parser'
